COPYING
MANIFEST.in
README.md
setup.py
elasticpy/__init__.py
elasticpy/bulk.py
elasticpy/connection.py
elasticpy/facet.py
elasticpy/filter.py
elasticpy/map.py
elasticpy/query.py
elasticpy/search.py
elasticpy/sort.py
elasticpy.egg-info/PKG-INFO
elasticpy.egg-info/SOURCES.txt
elasticpy.egg-info/dependency_links.txt
elasticpy.egg-info/requires.txt
elasticpy.egg-info/top_level.txt