Metadata-Version: 1.0
Name: elasticpy
Version: 0.10
Summary: Python Wrapper for elasticsearch
Home-page: http://github.com/ooici/elasticpy/
Author: Luke Campbell
Author-email: LCampbell@ASAScience.com
License: Apache 2.0
Keywords: elasticsearch search wrapper
Platform: UNKNOWN
Classifier: License :: OSI Approved :: Apache Software License
Classifier: Topic :: Database :: Front-Ends
Classifier: Topic :: System :: Software Distribution
Classifier: Topic :: System :: Systems Administration
Classifier: Topic :: Utilities
